clashogram/__init__.py
clashogram/_clashogram.py
clashogram/locales/messages.pot
clashogram/locales/fa_IR/LC_MESSAGES/messages.mo
clashogram/locales/fa_IR/LC_MESSAGES/messages.po
clashogram/locales/ru/LC_MESSAGES/messages.mo
clashogram/locales/ru/LC_MESSAGES/messages.po
clashogram-0.9.1.dist-info/entry_points.txt
clashogram-0.9.1.dist-info/LICENSE.txt
clashogram-0.9.1.dist-info/WHEEL
clashogram-0.9.1.dist-info/METADATA
clashogram-0.9.1.dist-info/RECORD
