Metadata-Version: 2.1
Name: clashogram
Version: 0.9.1
Summary: Clash of Clans war moniting for telegram channels.
Home-page: https://github.com/mehdisadeghi/clashogram
License: UNKNOWN
Keywords: coc telegram clashofclans
Author: Mehdi Sadeghi
Author-email: mehdi@mehdix.org
Requires-Python: >=3.5
Classifier: Environment :: Console
Classifier: Natural Language :: Persian
Classifier: Natural Language :: English
Classifier: Development Status :: 4 - Beta
Classifier: Programming Language :: Python :: 3
Classifier: Intended Audience :: End Users/Desktop
Classifier: License :: OSI Approved :: MIT License
Requires-Dist: requests
Requires-Dist: jdatetime
Requires-Dist: pytz
Requires-Dist: python-dateutil
Requires-Dist: click
Requires-Dist: babel ; extra == "i18n"
Requires-Dist: pytest ; extra == "test"
Provides-Extra: i18n
Provides-Extra: test
